cortex_airflow/__init__.py
cortex_airflow/data_platform/__init__.py
cortex_airflow/data_platform/operators/__init__.py
cortex_airflow/data_platform/operators/databrew_operators.py
cortex_airflow/data_platform/operators/sid_operators.py
cortex_airflow/data_platform/sensors/__init__.py
cortex_airflow/data_platform/sensors/sid_sensors.py
cortex_airflow/data_platform/task_groups/__init__.py
cortex_airflow/data_platform/task_groups/emr_groups.py
cortex_airflow/data_platform/task_groups/sid_groups.py
cortex_airflow/data_platform/utils/__init__.py
cortex_airflow/data_platform/utils/airflow_utils.py
cortex_airflow/data_platform/utils/aws_utils.py
cortex_airflow/data_platform/utils/file_utils.py
cortex_airflow/data_platform/utils/http_utils.py
cortex_airflow/data_platform/utils/sid_utils.py
cortex_airflow/data_platform/utils/slack_utils.py
cortex_airflow/data_platform/utils/time_utils.py
cortex_airflow_lib-0.0.11.dist-info/LICENSE
cortex_airflow_lib-0.0.11.dist-info/METADATA
cortex_airflow_lib-0.0.11.dist-info/WHEEL
cortex_airflow_lib-0.0.11.dist-info/top_level.txt
cortex_airflow_lib-0.0.11.dist-info/RECORD
