Metadata-Version: 2.1
Name: cortex-airflow-lib
Version: 0.0.11
Summary: cortex airflow SDK
Classifier: Programming Language :: Python :: 3
Classifier: License :: OSI Approved :: MIT License
Classifier: Operating System :: OS Independent
License-File: LICENSE
Requires-Dist: awswrangler (<2.14.0,>=2.11.0)
Requires-Dist: pyarrow (<5.1.0,>=4.0.1)
Requires-Dist: python-version (>="3.7")
